tableauhyperapi/__init__.py
tableauhyperapi/catalog.py
tableauhyperapi/connection.py
tableauhyperapi/databasename.py
tableauhyperapi/date.py
tableauhyperapi/endpoint.py
tableauhyperapi/hyperexception.py
tableauhyperapi/hyperprocess.py
tableauhyperapi/hyperserviceversion.py
tableauhyperapi/inserter.py
tableauhyperapi/interval.py
tableauhyperapi/name.py
tableauhyperapi/result.py
tableauhyperapi/resultschema.py
tableauhyperapi/schemaname.py
tableauhyperapi/sql.py
tableauhyperapi/sqltype.py
tableauhyperapi/tabledefinition.py
tableauhyperapi/tablename.py
tableauhyperapi/timestamp.py
tableauhyperapi/warning.py
tableauhyperapi/bin/libtableauhyperapi.dylib
tableauhyperapi/bin/hyper/hyperd
tableauhyperapi/impl/__init__.py
tableauhyperapi/impl/cdef.py
tableauhyperapi/impl/cdef_compiled.py
tableauhyperapi/impl/converter.py
tableauhyperapi/impl/dll.py
tableauhyperapi/impl/dllutil.py
tableauhyperapi/impl/hapi.py
tableauhyperapi/impl/immutablelistwrapper.py
tableauhyperapi/impl/lib_h.py
tableauhyperapi/impl/schemaconverter.py
tableauhyperapi/impl/util.py
tableauhyperapi/impl/version.py
tableauhyperapi-0.0.24081.dist-info/HYPER_API_OSS_disclosure.txt
tableauhyperapi-0.0.24081.dist-info/LICENSE
tableauhyperapi-0.0.24081.dist-info/METADATA
tableauhyperapi-0.0.24081.dist-info/NOTICES.txt
tableauhyperapi-0.0.24081.dist-info/WHEEL
tableauhyperapi-0.0.24081.dist-info/top_level.txt
tableauhyperapi-0.0.24081.dist-info/RECORD
