Metadata-Version: 2.1
Name: tableauhyperapi
Version: 0.0.24081
Summary: Hyper API for Python
Home-page: https://tableau.github.io/hyper-db
Author: Salesforce, Inc.
Author-email: tableauhyperapi@tableau.com
License: Apache-2.0
Classifier: Programming Language :: Python :: 3
Classifier: Operating System :: POSIX :: Linux
Classifier: Operating System :: Microsoft :: Windows
Classifier: Operating System :: MacOS
Classifier: License :: OSI Approved :: Apache Software License
Requires-Python: >=3.6
License-File: HYPER_API_OSS_disclosure.txt
License-File: LICENSE
License-File: NOTICES.txt
Requires-Dist: cffi!=1.14.3,<2,>=1.12.2
